[
    {
        "id": "1",
        "title": "Name of store",
        "pics": "img/Rectangle 550 (8).png"
    },
    {
        "id": "1",
        "title": "Name of store",
        "pics": "img/Rectangle 550 (9).png"
    },
    {
        "id": "1",
        "title": "Name of store",
        "pics": "img/Rectangle 550 (10).png"
    },
    {
        "id": "1",
        "title": "Name of store",
        "pics": "img/Rectangle 550 (11).png"
    },
    {
        "id": "1",
        "title": "Name of store",
        "pics": "img/Rectangle 550 (9).png"
    }
]